kbatch/__init__.py
kbatch/_backend.py
kbatch/_core.py
kbatch/_types.py
kbatch/cli.py
kbatch_proxy/__init__.py
tests/__init__.py
tests/test_backend.py
tests/test_client.py
tests/test_core.py
kbatch-0.4.2.dist-info/METADATA
kbatch-0.4.2.dist-info/WHEEL
kbatch-0.4.2.dist-info/entry_points.txt
kbatch-0.4.2.dist-info/top_level.txt
kbatch-0.4.2.dist-info/RECORD
