Metadata-Version: 2.1
Name: kbatch
Version: 0.4.2
Summary: Submit batch jobs to Kubernetes.
Home-page: https://github.com/kbatch-dev/kbatch
Author: Tom Augspurger
Author-email: taugspurger@microsoft.com
Requires-Dist: click
Requires-Dist: rich
Requires-Dist: httpx
Requires-Dist: pyyaml
Requires-Dist: kubernetes
Provides-Extra: all
Requires-Dist: sphinx ; extra == 'all'
Requires-Dist: myst-parser ; extra == 'all'
Requires-Dist: sphinx-click ; extra == 'all'
Requires-Dist: pydata-sphinx-theme ; extra == 'all'
Requires-Dist: pytest ; extra == 'all'
Requires-Dist: respx ; extra == 'all'
Requires-Dist: mypy ; extra == 'all'
Requires-Dist: types-PyYAML ; extra == 'all'
Requires-Dist: pre-commit ; extra == 'all'
Provides-Extra: docs
Requires-Dist: sphinx ; extra == 'docs'
Requires-Dist: myst-parser ; extra == 'docs'
Requires-Dist: sphinx-click ; extra == 'docs'
Requires-Dist: pydata-sphinx-theme ; extra == 'docs'
Provides-Extra: test
Requires-Dist: pytest ; extra == 'test'
Requires-Dist: respx ; extra == 'test'
Requires-Dist: mypy ; extra == 'test'
Requires-Dist: types-PyYAML ; extra == 'test'
Requires-Dist: pre-commit ; extra == 'test'
